esgtoolkit/__init__.py
esgtoolkit/config.py
esgtoolkit/esgcortest.py
esgtoolkit/esgdiscountfactor.py
esgtoolkit/esgfwdrates.py
esgtoolkit/esgmartingaletest.py
esgtoolkit/esgmccv.py
esgtoolkit/esgmcprices.py
esgtoolkit/esgplotbands.py
esgtoolkit/esgplotshocks.py
esgtoolkit/esgplotts.py
esgtoolkit/simdiff.py
esgtoolkit/simshocks.py
esgtoolkit/ycextra.py
esgtoolkit/ycinter.py
esgtoolkit-1.10.1.dist-info/licenses/LICENSE
esgtoolkit-1.10.1.dist-info/METADATA
esgtoolkit-1.10.1.dist-info/WHEEL
esgtoolkit-1.10.1.dist-info/top_level.txt
esgtoolkit-1.10.1.dist-info/RECORD
