Metadata-Version: 2.4
Name: esgtoolkit
Version: 1.10.1
Summary: Diffusion models for finance, insurance, economics, physics
Home-page: https://github.com/Techtonique/esgtoolkit_python
Author: T. Moudiki
Author-email: thierry.moudiki@gmail.com
License: BSD Clause Clear license
Keywords: esgtoolkit
Classifier: Development Status :: 2 - Pre-Alpha
Classifier: Intended Audience :: Developers
Classifier: License :: OSI Approved :: BSD License
Classifier: Natural Language :: English
Classifier: Programming Language :: Python :: 3
Classifier: Programming Language :: Python :: 3.6
Classifier: Programming Language :: Python :: 3.7
Classifier: Programming Language :: Python :: 3.8
Requires-Python: >=3.6
License-File: LICENSE
Requires-Dist: numpy
Requires-Dist: pandas
Requires-Dist: rpy2>=3.4.5
Requires-Dist: scipy
Dynamic: author
Dynamic: author-email
Dynamic: classifier
Dynamic: description
Dynamic: home-page
Dynamic: keywords
Dynamic: license
Dynamic: license-file
Dynamic: requires-dist
Dynamic: requires-python
Dynamic: summary
